{
  "last_update": "2026-03-11T23:27:34.481071",
  "incidents": [
    {
      "title": "#VíaLibre en #Nayarit tras #AccidenteVíal cerca del km 089+800, de la autopista Guadalajara - Tepic. Maneje con precaución.",
      "type": "twitter",
      "lat": 20.6597,
      "lng": -103.3496,
      "road": null,
      "km": 89.8,
      "risk": "high",
      "url": "https://nitter.net/GN_Carreteras/status/2031864686182862984#m",
      "timestamp": "2026-03-11T22:47:46+00:00",
      "timestamp_display": "11/03/2026 22:47 UTC",
      "segment": null
    },
    {
      "title": "#Tomeprecauciones en #Queretaro se registra cierre total tras #AccidenteVial cerca del km 161+100, de la carretera México - Querétaro. Atienda indicación vial.",
      "type": "twitter",
      "lat": 20.5888,
      "lng": -100.3899,
      "road": null,
      "km": 161.1,
      "risk": "high",
      "url": "https://nitter.net/GN_Carreteras/status/2031860646799663457#m",
      "timestamp": "2026-03-11T22:31:42+00:00",
      "timestamp_display": "11/03/2026 22:31 UTC",
      "segment": null
    },
    {
      "title": "#VíaLibre en #Guanajuato tras #AccidenteVial cerca del km 092+200, de la carretera Celaya - Ojuelos. Maneje con precaución.",
      "type": "twitter",
      "lat": 20.52,
      "lng": -100.81,
      "road": null,
      "km": 92.2,
      "risk": "high",
      "url": "https://nitter.net/GN_Carreteras/status/2031853889260306538#m",
      "timestamp": "2026-03-11T22:04:51+00:00",
      "timestamp_display": "11/03/2026 22:04 UTC",
      "segment": null
    },
    {
      "title": "#Tomeprecauciones en #Guanajuato se registra cierre total tras #AccidenteVial cerca del km 073+000, de la carretera Querétaro - Irapuato. Atienda indicación vial.",
      "type": "twitter",
      "lat": 20.5888,
      "lng": -100.3899,
      "road": null,
      "km": 73.0,
      "risk": "high",
      "url": "https://nitter.net/GN_Carreteras/status/2031846925717422313#m",
      "timestamp": "2026-03-11T21:37:11+00:00",
      "timestamp_display": "11/03/2026 21:37 UTC",
      "segment": null
    },
    {
      "title": "#VíaLibre en #Hidalgo tras #AccidenteVíal cerca del km 064+800, de la carretera Libramiento Norte. Maneje con precaución.",
      "type": "twitter",
      "lat": 23.5,
      "lng": -102.0,
      "road": null,
      "km": 64.8,
      "risk": "high",
      "url": "https://nitter.net/GN_Carreteras/status/2031843418352336958#m",
      "timestamp": "2026-03-11T21:23:15+00:00",
      "timestamp_display": "11/03/2026 21:23 UTC",
      "segment": null
    },
    {
      "title": "#Tomeprecauciones en #NuevoLeón se registra cierre parcial tras #AccidenteVial cerca del km 073+300, de la autopista Monterrey - Nuevo Laredo. Atienda indicación vial.",
      "type": "twitter",
      "lat": 26.294234792235716,
      "lng": -100.08419119315563,
      "road": 85,
      "km": 53.3,
      "risk": "high",
      "url": "https://nitter.net/GN_Carreteras/status/2031833673259974962#m",
      "timestamp": "2026-03-11T20:44:32+00:00",
      "timestamp_display": "11/03/2026 20:44 UTC",
      "segment": [
        "monterrey",
        "nuevo laredo"
      ]
    },
    {
      "title": "#Tomeprecauciones en #Guanajuato se registra cierre parcial tras #AccidenteVial cerca del km 092+200, de la carretera Celaya - Ojuelos. Atienda indicación vial.",
      "type": "twitter",
      "lat": 20.52,
      "lng": -100.81,
      "road": null,
      "km": 92.2,
      "risk": "high",
      "url": "https://nitter.net/GN_Carreteras/status/2031831642898063623#m",
      "timestamp": "2026-03-11T20:36:27+00:00",
      "timestamp_display": "11/03/2026 20:36 UTC",
      "segment": null
    },
    {
      "title": "🟠 CARGA VEHICULAR 🟠\nAutopista Querétaro - Irapuato, km 73, dirección Querétaro. El accidente ha sido atendido. Sin embargo, en la zona se registra carga vehicular. Maneja con precaución.",
      "type": "twitter",
      "lat": 20.5888,
      "lng": -100.3899,
      "road": null,
      "km": 73,
      "risk": "high",
      "url": "https://nitter.net/CAPUFE/status/2031874691292635464#m",
      "timestamp": "2026-03-11T23:27:31+00:00",
      "timestamp_display": "11/03/2026 23:27 UTC",
      "segment": null
    },
    {
      "title": "🟠 CARGA VEHICULAR 🟠\n#AutMéxicoQuerétaro, km 70, dirección CDMX. El accidente ha sido atendido. En la zona se registra carga vehicular. Maneja con precaución.",
      "type": "twitter",
      "lat": 20.5888,
      "lng": -100.3899,
      "road": null,
      "km": 70,
      "risk": "high",
      "url": "https://nitter.net/CAPUFE/status/2031874387738312985#m",
      "timestamp": "2026-03-11T23:26:19+00:00",
      "timestamp_display": "11/03/2026 23:26 UTC",
      "segment": null
    },
    {
      "title": "🟠 CIERRE PARCIAL DE CIRCULACIÓN 🟠\nAutopista Acatzingo - Cd. Mendoza, km 197, dirección Acatzingo. Reducción de carriles por atención de accidente (choque de costado entre tracto camiones). Maneja con precaución.",
      "type": "twitter",
      "lat": 23.5,
      "lng": -102.0,
      "road": null,
      "km": 197,
      "risk": "high",
      "url": "https://nitter.net/CAPUFE/status/2031873791559942451#m",
      "timestamp": "2026-03-11T23:23:56+00:00",
      "timestamp_display": "11/03/2026 23:23 UTC",
      "segment": null
    },
    {
      "title": "🟠 CARGA VEHICULAR 🟠       \nAutopista Puebla - Acatzingo, Plaza de Cobro Amozoc. Continúa carga vehicular en dirección Puebla, sin reporte de incidentes. Maneja con precaución.",
      "type": "twitter",
      "lat": 19.0414,
      "lng": -98.2063,
      "road": null,
      "km": null,
      "risk": "normal",
      "url": "https://nitter.net/CAPUFE/status/2031867844888306059#m",
      "timestamp": "2026-03-11T23:00:19+00:00",
      "timestamp_display": "11/03/2026 23:00 UTC",
      "segment": null
    },
    {
      "title": "🟠CARGA VEHICULAR🟠\n#AutMéxicoQuerétaro, km 90, dirección CDMX. Continúa carga vehicular a la altura de la gasa de incorporación a la Autopista Arco Norte, por incidente fuera de la cobertura de CAPUFE. Para más información llama al 8003272666 de @arconorte. Maneja con precaución.",
      "type": "twitter",
      "lat": 20.5888,
      "lng": -100.3899,
      "road": null,
      "km": 90,
      "risk": "normal",
      "url": "https://nitter.net/CAPUFE/status/2031867471960191444#m",
      "timestamp": "2026-03-11T22:58:50+00:00",
      "timestamp_display": "11/03/2026 22:58 UTC",
      "segment": null
    },
    {
      "title": "🟠 CIERRE PARCIAL DE CIRCULACIÓN 🟠\nAut. Nuevo Teapa - Cosoleacaque, km 16. Se restablece la circulación con reducción de carriles en ambos sentidos, por labores de mantenimiento sobre el Puente Ing. Antonio Dovalí Jaime. En la zona se registra carga vehicular. Maneja con precaución.",
      "type": "twitter",
      "lat": 18.0,
      "lng": -94.63,
      "road": null,
      "km": 16,
      "risk": "normal",
      "url": "https://nitter.net/CAPUFE/status/2031866848522928152#m",
      "timestamp": "2026-03-11T22:56:21+00:00",
      "timestamp_display": "11/03/2026 22:56 UTC",
      "segment": null
    },
    {
      "title": "R to @CAPUFE: ☑️ ACTUALIZACIÓN.\n#AutMéxicoQuerétaro, km 162, dirección Querétaro. Se informa a las personas usuarias que el accidente ha sido atendido, por lo que se restablece la circulación. Sin embargo, en la zona se registra carga vehicular. Maneja con precaución. Para más información por favor llama al 0⃣7⃣4⃣.",
      "type": "twitter",
      "lat": 20.5888,
      "lng": -100.3899,
      "road": null,
      "km": 162,
      "risk": "high",
      "url": "https://nitter.net/CAPUFE/status/2031860390939017409#m",
      "timestamp": "2026-03-11T22:30:41+00:00",
      "timestamp_display": "11/03/2026 22:30 UTC",
      "segment": null
    },
    {
      "title": "R to @CAPUFE: 🟢 RESTABLECIMIENTO DE CIRCULACIÓN 🟢\n#AutMéxicoQuerétaro, km 162, dirección Querétaro. Se informa a las personas usuarias que el accidente ha sido atendido. Tramo opera de manera normal. Maneja con precaución. 🚌🚙🚗🏍️",
      "type": "twitter",
      "lat": 20.5888,
      "lng": -100.3899,
      "road": null,
      "km": 162,
      "risk": "high",
      "url": "https://nitter.net/CAPUFE/status/2031865397872587144#m",
      "timestamp": "2026-03-11T22:50:35+00:00",
      "timestamp_display": "11/03/2026 22:50 UTC",
      "segment": null
    },
    {
      "title": "🟠 CIERRE PARCIAL DE CIRCULACIÓN 🟠\nAutopista Nuevo Teapa - Cosoleacaque, km 16. Continúa circulación intermitente en ambos sentidos, por labores de mantenimiento sobre el Puente Ing. Antonio Dovalí Jaime. En la zona se registra carga vehicular. Maneja con precaución.",
      "type": "twitter",
      "lat": 18.0,
      "lng": -94.63,
      "road": null,
      "km": 16,
      "risk": "normal",
      "url": "https://nitter.net/CAPUFE/status/2031863478752043351#m",
      "timestamp": "2026-03-11T22:42:58+00:00",
      "timestamp_display": "11/03/2026 22:42 UTC",
      "segment": null
    },
    {
      "title": "🟠 CIERRE PARCIAL DE CIRCULACIÓN 🟠\n#AutMéxicoQuerétaro, km 70, dirección CDMX. Se restablece la circulación con reducción de carriles. El personal continúa laborando en la atención del accidente (maniobras para el retiro de unidad siniestrada). En la zona se registra carga vehicular. Maneja con precaución. Para más información llama al 0⃣7⃣4⃣.",
      "type": "twitter",
      "lat": 20.5888,
      "lng": -100.3899,
      "road": null,
      "km": 70,
      "risk": "high",
      "url": "https://nitter.net/CAPUFE/status/2031863182927736981#m",
      "timestamp": "2026-03-11T22:41:47+00:00",
      "timestamp_display": "11/03/2026 22:41 UTC",
      "segment": null
    },
    {
      "title": "🔴 CIERRE DE CIRCULACIÓN 🔴\n#AutMéxicoQuerétaro, km 70, dirección CDMX. Cierre a la circulación por atención de accidente (maniobras para el retiro de la unidad siniestrada). Toma tus precauciones. Para más información llama al 0⃣7⃣4⃣.",
      "type": "twitter",
      "lat": 20.5888,
      "lng": -100.3899,
      "road": null,
      "km": 70,
      "risk": "high",
      "url": "https://nitter.net/CAPUFE/status/2031861038363394122#m",
      "timestamp": "2026-03-11T22:33:16+00:00",
      "timestamp_display": "11/03/2026 22:33 UTC",
      "segment": null
    },
    {
      "title": "🔴 CIERRE DE CIRCULACIÓN 🔴  \nAutopista Querétaro - Irapuato, km 73, dirección Querétaro. Continúa cierre a la circulación por atención de accidente (maniobras para el retiro de unidad siniestrada). Toma tus precauciones. Para más información llama al 0⃣7⃣4⃣.",
      "type": "twitter",
      "lat": 20.5888,
      "lng": -100.3899,
      "road": null,
      "km": 73,
      "risk": "high",
      "url": "https://nitter.net/CAPUFE/status/2031859067191509278#m",
      "timestamp": "2026-03-11T22:25:26+00:00",
      "timestamp_display": "11/03/2026 22:25 UTC",
      "segment": null
    },
    {
      "title": "🚧OBRAS Y LABORES DE MANTENIMIENTO🚧\nAutopista Cd. Mendoza - Córdoba, km 266, dirección Córdoba. Reducción de carriles por labores de mantenimiento. En la zona se registra carga vehicular. Maneja con precaución.",
      "type": "twitter",
      "lat": 18.8885,
      "lng": -96.9369,
      "road": null,
      "km": 266,
      "risk": "high",
      "url": "https://nitter.net/CAPUFE/status/2031853110923313507#m",
      "timestamp": "2026-03-11T22:01:46+00:00",
      "timestamp_display": "11/03/2026 22:01 UTC",
      "segment": null
    },
    {
      "title": "🚧OBRAS Y LABORES DE MANTENIMIENTO🚧  \nAutopista La Carbonera - Puerto México, del km 228 al 231, dirección La Carbonera. Reducción de carriles por labores de mantenimiento. En la zona se registra carga vehicular. Maneja con precaución.",
      "type": "twitter",
      "lat": 25.1685,
      "lng": -100.7189,
      "road": null,
      "km": 228,
      "risk": "high",
      "url": "https://nitter.net/CAPUFE/status/2031852668855918954#m",
      "timestamp": "2026-03-11T22:00:00+00:00",
      "timestamp_display": "11/03/2026 22:00 UTC",
      "segment": null
    },
    {
      "title": "🚧OBRAS Y LABORES DE MANTENIMIENTO🚧\n#AutMéxicoQuerétaro, km 165, dirección Querétaro. Continúa reducción de carriles por labores de mantenimiento. En la zona se registra carga vehicular. Maneja con precaución.",
      "type": "twitter",
      "lat": 20.5888,
      "lng": -100.3899,
      "road": null,
      "km": 165,
      "risk": "high",
      "url": "https://nitter.net/CAPUFE/status/2031852667656683935#m",
      "timestamp": "2026-03-11T22:00:00+00:00",
      "timestamp_display": "11/03/2026 22:00 UTC",
      "segment": null
    },
    {
      "title": "🚧OBRAS Y LABORES DE MANTENIMIENTO🚧\n#AutMéxicoQuerétaro, del km 194 al 207, dirección Querétaro. Continúa reducción de carriles por labores de mantenimiento. En la zona se registra carga vehicular. Maneja con precaución.",
      "type": "twitter",
      "lat": 20.5888,
      "lng": -100.3899,
      "road": null,
      "km": 194,
      "risk": "high",
      "url": "https://nitter.net/CAPUFE/status/2031852667320873243#m",
      "timestamp": "2026-03-11T22:00:00+00:00",
      "timestamp_display": "11/03/2026 22:00 UTC",
      "segment": null
    },
    {
      "title": "🟠 CIERRE PARCIAL DE CIRCULACIÓN 🟠\n#AutMéxicoQuerétaro, km 70, dirección CDMX. Reducción de carriles por atención de accidente (maniobras para el retiro de unidad siniestrada). Maneja con precaución.",
      "type": "twitter",
      "lat": 20.5888,
      "lng": -100.3899,
      "road": null,
      "km": 70,
      "risk": "high",
      "url": "https://nitter.net/CAPUFE/status/2031850627136151557#m",
      "timestamp": "2026-03-11T21:51:54+00:00",
      "timestamp_display": "11/03/2026 21:51 UTC",
      "segment": null
    },
    {
      "title": "🟢 RESTABLECIMIENTO DE CIRCULACIÓN 🟢\nAutopista La Tinaja - Isla, km 21, dirección La Tinaja. El accidente ha sido atendido. Tramo opera de manera normal. Maneja con precaución. 🚌🚙🚗🏍️",
      "type": "twitter",
      "lat": 23.5,
      "lng": -102.0,
      "road": null,
      "km": 21,
      "risk": "high",
      "url": "https://nitter.net/CAPUFE/status/2031847067078049816#m",
      "timestamp": "2026-03-11T21:37:45+00:00",
      "timestamp_display": "11/03/2026 21:37 UTC",
      "segment": null
    },
    {
      "title": "🔴 CIERRE DE CIRCULACIÓN 🔴\nAutopista Querétaro - Irapuato, km 73, dirección Querétaro. Cierre a la circulación por atención de accidente (choque contra barrera metálica de tracto camión). Toma tus precauciones. Para más información llama al 0⃣7⃣4⃣.",
      "type": "twitter",
      "lat": 20.5888,
      "lng": -100.3899,
      "road": null,
      "km": 73,
      "risk": "high",
      "url": "https://nitter.net/CAPUFE/status/2031846669852295551#m",
      "timestamp": "2026-03-11T21:36:10+00:00",
      "timestamp_display": "11/03/2026 21:36 UTC",
      "segment": null
    },
    {
      "title": "🔴CIERRE DE CIRCULACIÓN🔴\n\n⚠️ #IncidenteVial en #ArcoNorte\n\n📍Km 066+100 en sentido a Texmelucan.\n🛣️Tramo Querétaro - Tula 2.\n🟠Tome rutas alternas.\n🟠Ultima salida dirección Puebla, si viene de Atlacomulco es: Querétaro.\n\nInformes:*⃣2⃣6⃣8⃣",
      "type": "twitter",
      "lat": 20.5888,
      "lng": -100.3899,
      "road": null,
      "km": 66.1,
      "risk": "normal",
      "url": "https://nitter.net/arconorte/status/2031861911055179827#m",
      "timestamp": "2026-03-11T22:36:44+00:00",
      "timestamp_display": "11/03/2026 22:36 UTC",
      "segment": null
    },
    {
      "title": "🟢RESTABLECIMIENTO DE CIRCULACIÓN🟢\n\n➡️Se abre circulación en dirección a Texmelucan por el carril de alta; en el accidente de km 065. Tramo Querétaro - Tula 2. Carga vehicular en la zona, circule con precaución⚠️\n\n⬅️En dirección a Querétaro se opera de manera normal.",
      "type": "twitter",
      "lat": 20.5888,
      "lng": -100.3899,
      "road": null,
      "km": 65,
      "risk": "high",
      "url": "https://nitter.net/arconorte/status/2031840799592169661#m",
      "timestamp": "2026-03-11T21:12:51+00:00",
      "timestamp_display": "11/03/2026 21:12 UTC",
      "segment": null
    }
  ]
}