{
  "last_update": "2026-06-15T22:56:28.257655",
  "incidents": [
    {
      "title": "#ViaLibre en #Sinaloa tras presencia de personas cerca del km 019+300, de la carretera Culiacán-Los Mochis, a la altura de la Caseta de Cobro No. 10 Puente Culiacán.  Maneje con precaución.",
      "type": "twitter",
      "lat": 24.8,
      "lng": -107.39,
      "road": null,
      "km": 19.3,
      "risk": "normal",
      "url": "https://nitter.net/GN_Carreteras/status/2066651028867486159#m",
      "timestamp": "2026-06-15T22:36:16+00:00",
      "timestamp_display": "15/06/2026 16:36 CST",
      "segment": null
    },
    {
      "title": "#ViaLibre en #EdoMx tras presencia de personas cerca del km 033+000, de la carretera México-Puebla, en la Caseta de Cobro No. 7, San Marcos. Maneje con precaución.",
      "type": "twitter",
      "lat": 19.294432924042745,
      "lng": -98.87751001702294,
      "road": 150,
      "km": 15.0,
      "risk": "normal",
      "url": "https://nitter.net/GN_Carreteras/status/2066649342622998809#m",
      "timestamp": "2026-06-15T22:29:34+00:00",
      "timestamp_display": "15/06/2026 16:29 CST",
      "segment": [
        "mexico",
        "puebla"
      ]
    },
    {
      "title": "#Tomeprecauciones continua en #Sinaloa presencia de personas cerca del km 019+300, de la carretera Culiacán-Los Mochis, a la altura de la Caseta de Cobro No. 10 Puente Culiacán. La Caseta labora libre de peaje. Atienda indicación vial.",
      "type": "twitter",
      "lat": 24.8,
      "lng": -107.39,
      "road": null,
      "km": 19.3,
      "risk": "normal",
      "url": "https://nitter.net/GN_Carreteras/status/2066640057771982883#m",
      "timestamp": "2026-06-15T21:52:40+00:00",
      "timestamp_display": "15/06/2026 15:52 CST",
      "segment": null
    },
    {
      "title": "🟢 SE RETIRAN MANIFESTANTES 🟢\nAutopista Tehuacán - Oaxaca, Plaza de Cobro Huitzo. Se informa a las personas usuarias que se retiran los manifestantes. Tramo opera de manera normal en ambos sentidos. Maneja con precaución. 🚌🚙🚗🏍️",
      "type": "twitter",
      "lat": 17.072,
      "lng": -96.72,
      "road": null,
      "km": null,
      "risk": "normal",
      "url": "https://nitter.net/CAPUFE/status/2066655253848543392#m",
      "timestamp": "2026-06-15T22:53:03+00:00",
      "timestamp_display": "15/06/2026 16:53 CST",
      "segment": null
    },
    {
      "title": "🟠 CIERRE PARCIAL DE CIRCULACIÓN 🟠\n#AutMéxicoCuernavaca, km 63, dirección Cuernavaca. Reducción de carriles por atención de accidente (salida del camino de automóvil). Maneja con precaución.",
      "type": "twitter",
      "lat": 18.93,
      "lng": -99.22,
      "road": null,
      "km": 63,
      "risk": "high",
      "url": "https://nitter.net/CAPUFE/status/2066654915120783449#m",
      "timestamp": "2026-06-15T22:51:43+00:00",
      "timestamp_display": "15/06/2026 16:51 CST",
      "segment": null
    },
    {
      "title": "🌧️🌩️ CONDICIONES CLIMÁTICAS 🌧️🌩️​   \nAutopista Chamapa - Lechería, registra #lluvia. Disminuye tu velocidad y maneja con precaución.",
      "type": "twitter",
      "lat": 23.5,
      "lng": -102.0,
      "road": null,
      "km": null,
      "risk": "normal",
      "url": "https://nitter.net/CAPUFE/status/2066652822184038779#m",
      "timestamp": "2026-06-15T22:43:24+00:00",
      "timestamp_display": "15/06/2026 16:43 CST",
      "segment": null
    },
    {
      "title": "🟠 CIERRE PARCIAL DE CIRCULACIÓN 🟠\nAutopista Tehuacán - Oaxaca, km 100. Circulación intermitente en ambos sentidos por atención de accidente (salida del camino y choque contra barreras metálicas). En la zona se registra carga vehicular. Maneja con precaución.",
      "type": "twitter",
      "lat": 17.072,
      "lng": -96.72,
      "road": null,
      "km": 100,
      "risk": "high",
      "url": "https://nitter.net/CAPUFE/status/2066651686869848551#m",
      "timestamp": "2026-06-15T22:38:53+00:00",
      "timestamp_display": "15/06/2026 16:38 CST",
      "segment": null
    },
    {
      "title": "🟠 CIERRE PARCIAL DE CIRCULACIÓN 🟠\nAutopista La Tinaja - Isla, km 48, dirección La Tinaja. Reducción de carriles por atención de accidente (salida del camino y volcadura de camión de carga). Maneja con precaución.",
      "type": "twitter",
      "lat": 18.7603,
      "lng": -96.4616,
      "road": null,
      "km": 48,
      "risk": "high",
      "url": "https://nitter.net/CAPUFE/status/2066647562342338592#m",
      "timestamp": "2026-06-15T22:22:29+00:00",
      "timestamp_display": "15/06/2026 16:22 CST",
      "segment": null
    },
    {
      "title": "🟠 CIERRE PARCIAL DE CIRCULACIÓN 🟠\nAutopista Isla - Acayucan, km 160, dirección Acayucan. Reducción de carriles por atención de accidente (salida del camino y volcadura de camión de carga). Maneja con precaución.",
      "type": "twitter",
      "lat": 17.94,
      "lng": -94.91,
      "road": null,
      "km": 160,
      "risk": "high",
      "url": "https://nitter.net/CAPUFE/status/2066647292170428453#m",
      "timestamp": "2026-06-15T22:21:25+00:00",
      "timestamp_display": "15/06/2026 16:21 CST",
      "segment": null
    },
    {
      "title": "⚠️ PRESENCIA DE MANIFESTANTES ⚠️\nAutopista Tehuacán - Oaxaca, Plaza de Cobro Huitzo. Continúa presencia de manifestantes en ambos sentidos, sin cierre a la circulación. Maneja con precaución.",
      "type": "twitter",
      "lat": 17.072,
      "lng": -96.72,
      "road": null,
      "km": null,
      "risk": "normal",
      "url": "https://nitter.net/CAPUFE/status/2066645767029227880#m",
      "timestamp": "2026-06-15T22:15:21+00:00",
      "timestamp_display": "15/06/2026 16:15 CST",
      "segment": null
    },
    {
      "title": "🌧️🌩️  CONDICIONES CLIMÁTICAS  🌧️🌩️  \nAutopista Cd. Mendoza - Córdoba, registra #lluvia. Disminuye tu velocidad y maneja con precaución.",
      "type": "twitter",
      "lat": 18.8885,
      "lng": -96.9369,
      "road": null,
      "km": null,
      "risk": "normal",
      "url": "https://nitter.net/CAPUFE/status/2066644963698360814#m",
      "timestamp": "2026-06-15T22:12:10+00:00",
      "timestamp_display": "15/06/2026 16:12 CST",
      "segment": null
    },
    {
      "title": "🟢 SE RETIRAN MANIFESTANTES 🟢\nAutopista Tijuana - Ensenada, Plazas de Cobro Playas de Tijuana y Ensenada. Se informa a las personas usuarias que se retiran los manifestantes. Tramo opera de manera normal en ambos sentidos. Maneja con precaución. 🚌🚙🚗🏍️",
      "type": "twitter",
      "lat": 32.5127,
      "lng": -116.9301,
      "road": null,
      "km": null,
      "risk": "normal",
      "url": "https://nitter.net/CAPUFE/status/2066644392132104619#m",
      "timestamp": "2026-06-15T22:09:54+00:00",
      "timestamp_display": "15/06/2026 16:09 CST",
      "segment": null
    },
    {
      "title": "🔴 CIERRE DE CIRCULACIÓN 🔴\n#AutMéxicoPuebla, km 59, dirección CDMX. Continúa cierre a la circulación por atención de accidente (maniobras para retiro de unidad siniestrada).\n\n➡ Dir. Puebla, se restablece la circulación con reducción de carriles. En la zona se registra reducción de carriles.\n\nToma tus precauciones. Para más información llama al 0⃣7⃣4⃣.",
      "type": "twitter",
      "lat": 19.331674540802503,
      "lng": -98.69475909769841,
      "road": 150,
      "km": 41,
      "risk": "high",
      "url": "https://nitter.net/CAPUFE/status/2066641278964511100#m",
      "timestamp": "2026-06-15T21:57:31+00:00",
      "timestamp_display": "15/06/2026 15:57 CST",
      "segment": [
        "mexico",
        "puebla"
      ]
    },
    {
      "title": "🟢 RESTABLECIMIENTO DE CIRCULACIÓN 🟢\nLibramiento Cuernavaca, km 86, dirección Acapulco. El accidente ha sido atendido. Tramo opera de manera normal. Maneja con precaución. 🚌🚙🚗🏍️",
      "type": "twitter",
      "lat": 18.93,
      "lng": -99.22,
      "road": null,
      "km": 86,
      "risk": "high",
      "url": "https://nitter.net/CAPUFE/status/2066640627136164106#m",
      "timestamp": "2026-06-15T21:54:56+00:00",
      "timestamp_display": "15/06/2026 15:54 CST",
      "segment": null
    },
    {
      "title": "🟠 CIERRE PARCIAL DE CIRCULACIÓN 🟠\nAutopista La Tinaja - Isla, km 42, dirección Isla. Reducción de carriles por atención de accidente (salida del camino y volcadura de camión de carga). Maneja con precaución.",
      "type": "twitter",
      "lat": 18.7603,
      "lng": -96.4616,
      "road": null,
      "km": 42,
      "risk": "high",
      "url": "https://nitter.net/CAPUFE/status/2066630442472689696#m",
      "timestamp": "2026-06-15T21:14:28+00:00",
      "timestamp_display": "15/06/2026 15:14 CST",
      "segment": null
    },
    {
      "title": "🚧🚑 En autopistas de #CAPUFE, los servicios de apoyo son gratuitos.\nNo permitas abusos.\nSi alguien solicita dinero por brindarte asistencia, denuncia de inmediato.\n👉 800 990 2900 📩 quejas@capufe.gob.mx\n#EnCAPUFEEstamosParaServirte",
      "type": "twitter",
      "lat": 23.5,
      "lng": -102.0,
      "road": null,
      "km": null,
      "risk": "normal",
      "url": "https://nitter.net/CAPUFE/status/2066626802307776710#m",
      "timestamp": "2026-06-15T21:00:00+00:00",
      "timestamp_display": "15/06/2026 15:00 CST",
      "segment": null
    },
    {
      "title": "🟢 RESTABLECIMIENTO DE CIRCULACIÓN 🟢\n#AutMéxicoQuerétaro, km 161, dirección CDMX. El accidente ha sido atendido. Tramo opera de manera normal. Maneja con precaución. 🚌🚙🚗🏍️",
      "type": "twitter",
      "lat": 20.5888,
      "lng": -100.3899,
      "road": null,
      "km": 161,
      "risk": "high",
      "url": "https://nitter.net/CAPUFE/status/2066626361158951401#m",
      "timestamp": "2026-06-15T20:58:15+00:00",
      "timestamp_display": "15/06/2026 14:58 CST",
      "segment": null
    },
    {
      "title": "🟢 RESTABLECIMIENTO DE CIRCULACIÓN 🟢\n#AutMéxicoPuebla, km 37, dirección CDMX. El accidente ha sido atendido. Tramo opera de manera normal. Maneja con precaución. 🚌🚙🚗🏍️",
      "type": "twitter",
      "lat": 19.304815529828517,
      "lng": -98.84104582903784,
      "road": 150,
      "km": 19,
      "risk": "high",
      "url": "https://nitter.net/CAPUFE/status/2066625897218654637#m",
      "timestamp": "2026-06-15T20:56:24+00:00",
      "timestamp_display": "15/06/2026 14:56 CST",
      "segment": [
        "mexico",
        "puebla"
      ]
    },
    {
      "title": "⚠️ PRESENCIA DE MANIFESTANTES ⚠️\nSe informa a las personas usuarias que se registra presencia de manifestantes en diversos puntos de las autopistas administradas por CAPUFE, sin cierre a la circulación.\n\n🔘 Autopista Tehuacán - Oaxaca, Plaza de Cobro Huitzo, en ambos sentidos.\n🔘 Autopista Tijuana - Ensenada, Plaza de Cobro Playas de Tijuana, en ambos sentidos.\n\nCualquier cambio o novedad se dará a conocer por este medio o en el 0️⃣7️⃣4️⃣. Maneja con precaución.",
      "type": "twitter",
      "lat": 32.5127,
      "lng": -116.9301,
      "road": null,
      "km": null,
      "risk": "normal",
      "url": "https://nitter.net/CAPUFE/status/2066623639718412660#m",
      "timestamp": "2026-06-15T20:47:26+00:00",
      "timestamp_display": "15/06/2026 14:47 CST",
      "segment": null
    },
    {
      "title": "🟢 SE RETIRAN MANIFESTANTES 🟢\nAutopista Tijuana - Ensenada, Plazas de Cobro Ensenada. Se informa a las personas usuarias que se retiran los manifestantes. Tramo opera de manera normal en ambos sentidos. Maneja con precaución. 🚌🚙🚗🏍️",
      "type": "twitter",
      "lat": 32.5127,
      "lng": -116.9301,
      "road": null,
      "km": null,
      "risk": "normal",
      "url": "https://nitter.net/CAPUFE/status/2066623015048052994#m",
      "timestamp": "2026-06-15T20:44:57+00:00",
      "timestamp_display": "15/06/2026 14:44 CST",
      "segment": null
    },
    {
      "title": "⚠️ PRESENCIA DE MANIFESTANTES ⚠️\nSe informa a las personas usuarias que se registra presencia de manifestantes en diversos puntos de las autopistas administradas por CAPUFE, sin cierre a la circulación.\n\n🔘 Autopista Tehuacán - Oaxaca, Plaza de Cobro Huitzo, en ambos sentidos.\n🔘 Autopista Tijuana - Ensenada, Plazas de Cobro Playas de Tijuana y Ensenada, en ambos sentidos.\n\nCualquier cambio o novedad se dará a conocer por este medio o en el 0️⃣7️⃣4️⃣. Maneja con precaución.",
      "type": "twitter",
      "lat": 32.5127,
      "lng": -116.9301,
      "road": null,
      "km": null,
      "risk": "normal",
      "url": "https://nitter.net/CAPUFE/status/2066619964769898608#m",
      "timestamp": "2026-06-15T20:32:50+00:00",
      "timestamp_display": "15/06/2026 14:32 CST",
      "segment": null
    },
    {
      "title": "🟢 SE RETIRAN MANIFESTANTES 🟢\n#AutMéxicoCuernavaca, Plaza de Cobro Tlalpan. Se informa a las personas usuarias que se retiran los manifestantes. Tramo opera de manera normal en ambos sentidos. Maneja con precaución. 🚌🚙🚗🏍️",
      "type": "twitter",
      "lat": 18.93,
      "lng": -99.22,
      "road": null,
      "km": null,
      "risk": "normal",
      "url": "https://nitter.net/CAPUFE/status/2066619700067311811#m",
      "timestamp": "2026-06-15T20:31:47+00:00",
      "timestamp_display": "15/06/2026 14:31 CST",
      "segment": null
    },
    {
      "title": "🟠 CIERRE PARCIAL DE CIRCULACIÓN 🟠   \n#AutMéxicoPuebla, km 37, dirección CDMX. Continúa reducción de carriles por atención de accidente (labores de limpieza). Maneja con precaución.",
      "type": "twitter",
      "lat": 19.304815529828517,
      "lng": -98.84104582903784,
      "road": 150,
      "km": 19,
      "risk": "high",
      "url": "https://nitter.net/CAPUFE/status/2066619433695506819#m",
      "timestamp": "2026-06-15T20:30:43+00:00",
      "timestamp_display": "15/06/2026 14:30 CST",
      "segment": [
        "mexico",
        "puebla"
      ]
    }
  ]
}